moodist/__init__.py
moodist/_core.py
moodist/backend.py
moodist/compile.py
moodist/lib_serialize.cpython-310.so
moodist/lib_serialize.cpython-311.so
moodist/lib_serialize.cpython-312.so
moodist/lib_serialize.cpython-313.so
moodist/lib_serialize.cpython-314.so
moodist/libmoodist.so
moodist/options.py
moodist/queue.py
moodist/version.py
moodist/pt27/_C.abi3.so
moodist/pt28/_C.abi3.so
moodist/pt29/_C.abi3.so
moodist-0.10.0.dist-info/licenses/LICENSE
moodist-0.10.0.dist-info/METADATA
moodist-0.10.0.dist-info/WHEEL
moodist-0.10.0.dist-info/top_level.txt
moodist-0.10.0.dist-info/RECORD
