Metadata-Version: 2.4
Name: moodist
Version: 0.10.0
Summary: moodist
Home-page: 
Author: 
Classifier: Programming Language :: C++
Classifier: Programming Language :: Python :: 3
Classifier: License :: OSI Approved :: MIT License
Classifier: Operating System :: POSIX :: Linux
Classifier: Environment :: GPU :: NVIDIA CUDA
License-File: LICENSE
Requires-Dist: torch<2.10,>=2.7
Dynamic: classifier
Dynamic: description-content-type
Dynamic: license-file
Dynamic: requires-dist
Dynamic: summary
